.gitattributes
.gitignore
.readthedocs.yaml
CHANGELOG.md
CMakeLists.txt
LICENSE.md
README.md
dune-mmesh.pc.in
dune.module
pyproject.toml
setup.py
.github/workflows/dockerimage.yml
.github/workflows/test.yml
.github/workflows/testpypi.yml
CGAL/Aff_transformation_2.h
CGAL/Aff_transformation_3.h
CGAL/Algebraic_extension_traits.h
CGAL/Algebraic_structure_traits.h
CGAL/BOOST_MP_arithmetic_kernel.h
CGAL/Bbox_2.h
CGAL/Bbox_3.h
CGAL/CC_safe_handle.h
CGAL/Cache.h
CGAL/Cartesian_converter.h
CGAL/Cartesian_converter_fwd.h
CGAL/Chinese_remainder_traits.h
CGAL/Circle_2.h
CGAL/Circle_3.h
CGAL/Coercion_traits.h
CGAL/Compact_container.h
CGAL/Complexity_tags.h
CGAL/Concurrent_compact_container.h
CGAL/Conic_2.h
CGAL/Constrained_Delaunay_triangulation_face_base_2.h
CGAL/Constrained_triangulation_face_base_2.h
CGAL/Default.h
CGAL/Delaunay_mesh_face_base_2.h
CGAL/Delaunay_mesh_vertex_base_2.h
CGAL/Delaunay_triangulation_2.h
CGAL/Delaunay_triangulation_3.h
CGAL/Delaunay_triangulation_cell_base_3.h
CGAL/Dimension.h
CGAL/Direction_2.h
CGAL/Direction_3.h
CGAL/Dummy_tds_2.h
CGAL/Enum_converter.h
CGAL/Epic_converter.h
CGAL/Exact_kernel_selector.h
CGAL/Exact_predicates_exact_constructions_kernel.h
CGAL/Exact_predicates_inexact_constructions_kernel.h
CGAL/FPU.h
CGAL/Filtered_kernel.h
CGAL/Filtered_kernel_fwd.h
CGAL/Filtered_predicate.h
CGAL/Fraction_traits.h
CGAL/GMP_arithmetic_kernel.h
CGAL/Get_arithmetic_kernel.h
CGAL/Gmp_coercion_traits.h
CGAL/Gmpq.h
CGAL/Gmpz.h
CGAL/Gmpzf.h
CGAL/Handle.h
CGAL/Handle_for.h
CGAL/Handle_for_virtual.h
CGAL/Handle_hash_function.h
CGAL/Has_member.h
CGAL/Has_timestamp.h
CGAL/Hilbert_policy_tags.h
CGAL/Hilbert_sort_2.h
CGAL/Hilbert_sort_3.h
CGAL/Hilbert_sort_base.h
CGAL/Hilbert_sort_d.h
CGAL/Hilbert_sort_median_2.h
CGAL/Hilbert_sort_median_3.h
CGAL/Hilbert_sort_median_d.h
CGAL/Hilbert_sort_middle_2.h
CGAL/Hilbert_sort_middle_3.h
CGAL/Hilbert_sort_middle_base.h
CGAL/Hilbert_sort_middle_d.h
CGAL/Homogeneous_converter.h
CGAL/Intersection_traits.h
python/dune_mmesh.egg-info/PKG-INFO
python/dune_mmesh.egg-info/SOURCES.txt
python/dune_mmesh.egg-info/dependency_links.txt
python/dune_mmesh.egg-info/requires.txt
python/dune_mmesh.egg-info/top_level.txt
