Metadata-Version: 2.1
Name: dune-mmesh
Version: 1.4
Summary: MMesh is a grid implementation based on CGAL triangulations
Home-page: https://gitlab.dune-project.org/samuel.burbulla/dune-mmesh
Author: Samuel Burbulla
Author-email: samuel.burbulla@ians.uni-stuttgart.de
Classifier: Programming Language :: C++
Classifier: Programming Language :: Python :: 3
Classifier: License :: OSI Approved :: GNU General Public License (GPL)
Requires-Python: >=3.4
License-File: LICENSE.md
